odoo/addons/l10n_ro_stock_account_tracking/README.rst
odoo/addons/l10n_ro_stock_account_tracking/__init__.py
odoo/addons/l10n_ro_stock_account_tracking/__manifest__.py
odoo/addons/l10n_ro_stock_account_tracking/i18n/l10n_ro_stock_account.pot
odoo/addons/l10n_ro_stock_account_tracking/i18n/l10n_ro_stock_account_tracking.pot
odoo/addons/l10n_ro_stock_account_tracking/i18n/ro.po
odoo/addons/l10n_ro_stock_account_tracking/models/__init__.py
odoo/addons/l10n_ro_stock_account_tracking/models/stock_move.py
odoo/addons/l10n_ro_stock_account_tracking/models/stock_move_tracking.py
odoo/addons/l10n_ro_stock_account_tracking/readme/CONTRIBUTORS.md
odoo/addons/l10n_ro_stock_account_tracking/readme/DESCRIPTION.md
odoo/addons/l10n_ro_stock_account_tracking/security/ir.model.access.csv
odoo/addons/l10n_ro_stock_account_tracking/static/description/icon.png
odoo/addons/l10n_ro_stock_account_tracking/static/description/index.html
odoo/addons/l10n_ro_stock_account_tracking/tests/__init__.py
odoo/addons/l10n_ro_stock_account_tracking/tests/test_stock_move_tracking.py
odoo/addons/l10n_ro_stock_account_tracking/views/stock_move_views.xml
odoo_addon_l10n_ro_stock_account_tracking-19.0.0.1.0.dist-info/METADATA
odoo_addon_l10n_ro_stock_account_tracking-19.0.0.1.0.dist-info/WHEEL
odoo_addon_l10n_ro_stock_account_tracking-19.0.0.1.0.dist-info/top_level.txt
odoo_addon_l10n_ro_stock_account_tracking-19.0.0.1.0.dist-info/RECORD
